Workbook

Sheet Дашборд
A1: Столярная мастерская «Верстак-12» · дашборд 2025
A3: Выручка за год | C3: Расходы за год | E3: Чистая прибыль | G3: Рентабельность | I3: Лучший месяц по прибыли | K3: Деньги на 31.12 | O3: Структура расходов
A4: ='Сводка по месяцам'!N9 -> 20331400 | C4: ='Сводка по месяцам'!N22 -> 16175200 | E4: ='Сводка по месяцам'!N26 -> 4156200 | G4: ='Сводка по месяцам'!N27 -> 0.20442272 | I4: =INDEX('Сводка по месяцам'!B3:M3,MATCH(MAX('Сводка по месяцам'!B26:M26),'Сводка по месяцам'!B26:M26,0)) -> 45962 | K4: ='Сводка по месяцам'!N28 -> 4671200 | O4: Переменные | P4: =SUMPRODUCT(SUMIFS(Операции!$E$3:$E$1000,Операции!$B$3:$B$1000,Справочники!$A$4:$A$18)*(Справочники!$C$4:$C$18="Переменные")) -> 10444100
O5: Постоянные | P5: =SUMPRODUCT(SUMIFS(Операции!$E$3:$E$1000,Операции!$B$3:$B$1000,Справочники!$A$4:$A$18)*(Справочники!$C$4:$C$18="Постоянные")) -> 4511200
O6: Налоги | P6: =SUMPRODUCT(SUMIFS(Операции!$E$3:$E$1000,Операции!$B$3:$B$1000,Справочники!$A$4:$A$18)*(Справочники!$C$4:$C$18="Налоги")) -> 1219900

Sheet Справочники
A1: Столярная мастерская «Верстак-12» · справочники
A3: Статья | B3: Тип | C3: Группа | E3: Направление | G3: Счёт | H3: Остаток на 01.01
A4: Продажа кухонь | B4: Доход | C4: Выручка | E4: Кухни | G4: Расчётный счёт | H4: 420000
A5: Продажа шкафов | B5: Доход | C5: Выручка | E5: Шкафы и гардеробные | G5: Касса | H5: 35000
A6: Мелкая мебель | B6: Доход | C6: Выручка | E6: Мелкая мебель | G6: Карта | H6: 60000
A7: Монтаж и доставка | B7: Доход | C7: Выручка | E7: — | G7: Итого | H7: =SUM(H4:H6) -> 515000
A8: Материалы (ЛДСП, фасады) | B8: Расход | C8: Переменные
A9: Фурнитура | B9: Расход | C9: Переменные
A10: Сдельная оплата сборщиков | B10: Расход | C10: Переменные
A11: Транспорт | B11: Расход | C11: Переменные
A12: Зарплата (оклады) | B12: Расход | C12: Постоянные
A13: Аренда цеха | B13: Расход | C13: Постоянные
A14: Коммунальные услуги | B14: Расход | C14: Постоянные
A15: Реклама | B15: Расход | C15: Постоянные
A16: Инструмент и ремонт | B16: Расход | C16: Постоянные
A17: Бухгалтерия и банк | B17: Расход | C17: Постоянные
A18: Налоги (УСН) | B18: Расход | C18: Налоги
A21: Новую статью добавляйте в конец списка статей: она появится в выпадающем списке и попадёт в сводку после добавления строки на лист «Сводка по месяцам».

Sheet Операции
A1: Столярная мастерская «Верстак-12» · журнал операций
A2: Дата | B2: Статья | C2: Направление | D2: Счёт | E2: Сумма | F2: Комментарий | G2: Тип | H2: Месяц
A3: 45659 | B3: Мелкая мебель | C3: Мелкая мебель | D3: Касса | E3: 6800 | F3: Розница | G3: =IF(B3="","",IFERROR(VLOOKUP(B3,Справочники!$A$4:$C$18,2,FALSE()),"нет в справочнике")) -> Доход | H3: =IF(A3="","",DATE(YEAR(A3),MONTH(A3),1)) -> 45658
A4: 45662 | B4: Продажа шкафов | C4: Шкафы и гардеробные | D4: Карта | E4: 81300 | F4: Заказ Ш-476 | G4: =IF(B4="","",IFERROR(VLOOKUP(B4,Справочники!$A$4:$C$18,2,FALSE()),"нет в справочнике")) -> Доход | H4: =IF(A4="","",DATE(YEAR(A4),MONTH(A4),1)) -> 45658
A5: 45662 | B5: Аренда цеха | C5: — | D5: Расчётный счёт | E5: 85000 | F5: Аренда, 240 м² | G5: =IF(B5="","",IFERROR(VLOOKUP(B5,Справочники!$A$4:$C$18,2,FALSE()),"нет в справочнике")) -> Расход | H5: =IF(A5="","",DATE(YEAR(A5),MONTH(A5),1)) -> 45658
A6: 45664 | B6: Продажа шкафов | C6: Шкафы и гардеробные | D6: Расчётный счёт | E6: 76400 | F6: Заказ Ш-625 | G6: =IF(B6="","",IFERROR(VLOOKUP(B6,Справочники!$A$4:$C$18,2,FALSE()),"нет в справочнике")) -> Доход | H6: =IF(A6="","",DATE(YEAR(A6),MONTH(A6),1)) -> 45658
A7: 45664 | B7: Реклама | C7: — | D7: Карта | E7: 40400 | F7: Контекстная реклама | G7: =IF(B7="","",IFERROR(VLOOKUP(B7,Справочники!$A$4:$C$18,2,FALSE()),"нет в справочнике")) -> Расход | H7: =IF(A7="","",DATE(YEAR(A7),MONTH(A7),1)) -> 45658
A8: 45665 | B8: Продажа кухонь | C8: Кухни | D8: Расчётный счёт | E8: 175500 | F8: Заказ К-671 | G8: =IF(B8="","",IFERROR(VLOOKUP(B8,Справочники!$A$4:$C$18,2,FALSE()),"нет в справочнике")) -> Доход | H8: =IF(A8="","",DATE(YEAR(A8),MONTH(A8),1)) -> 45658
A9: 45665 | B9: Транспорт | C9: Шкафы и гардеробные | D9: Карта | E9: 30700 | F9: Доставка заказов | G9: =IF(B9="","",IFERROR(VLOOKUP(B9,Справочники!$A$4:$C$18,2,FALSE()),"нет в справочнике")) -> Расход | H9: =IF(A9="","",DATE(YEAR(A9),MONTH(A9),1)) -> 45658
A10: 45667 | B10: Материалы (ЛДСП, фасады) | C10: Кухни | D10: Расчётный счёт | E10: 79100 | F10: Поставка плит и фасадов | G10: =IF(B10="","",IFERROR(VLOOKUP(B10,Справочники!$A$4:$C$18,2,FALSE()),"нет в справочнике")) -> Расход | H10: =IF(A10="","",DATE(YEAR(A10),MONTH(A10),1)) -> 45658
A11: 45667 | B11: Зарплата (оклады) | C11: — | D11: Расчётный счёт | E11: 210000 | F11: Оклады за прошлый месяц | G11: =IF(B11="","",IFERROR(VLOOKUP(B11,Справочники!$A$4:$C$18,2,FALSE()),"нет в справочнике")) -> Расход | H11: =IF(A11="","",DATE(YEAR(A11),MONTH(A11),1)) -> 45658
A12: 45668 | B12: Продажа шкафов | C12: Шкафы и гардеробные | D12: Карта | E12: 82800 | F12: Заказ Ш-917 | G12: =IF(B12="","",IFERROR(VLOOKUP(B12,Справочники!$A$4:$C$18,2,FALSE()),"нет в справочнике")) -> Доход | H12: =IF(A12="","",DATE(YEAR(A12),MONTH(A12),1)) -> 45658
A13: 45669 | B13: Материалы (ЛДСП, фасады) | C13: Шкафы и гардеробные | D13: Расчётный счёт | E13: 83000 | F13: Поставка плит и фасадов | G13: =IF(B13="","",IFERROR(VLOOKUP(B13,Справочники!$A$4:$C$18,2,FALSE()),"нет в справочнике")) -> Расход | H13: =IF(A13="","",DATE(YEAR(A13),MONTH(A13),1)) -> 45658
A14: 45669 | B14: Фурнитура | C14: Шкафы и гардеробные | D14: Расчётный счёт | E14: 33400 | F14: Поставка фурнитуры | G14: =IF(B14="","",IFERROR(VLOOKUP(B14,Справочники!$A$4:$C$18,2,FALSE()),"нет в справочнике")) -> Расход | H14: =IF(A14="","",DATE(YEAR(A14),MONTH(A14),1)) -> 45658
... A401: 46022 | B401: Фурнитура | C401: Кухни | D401: Расчётный счёт | E401: 55300 | F401: Поставка фурнитуры | G401: =IF(B401="","",IFERROR(VLOOKUP(B401,Справочники!$A$4:$C$18,2,FALSE()),"нет в справочнике")) -> Расход | H401: =IF(A401="","",DATE(YEAR(A401),MONTH(A401),1)) -> 45992
G402: =IF(B402="","",IFERROR(VLOOKUP(B402,Справочники!$A$4:$C$18,2,FALSE()),"нет в справочнике")) | H402: =IF(A402="","",DATE(YEAR(A402),MONTH(A402),1))
G403: =IF(B403="","",IFERROR(VLOOKUP(B403,Справочники!$A$4:$C$18,2,FALSE()),"нет в справочнике")) | H403: =IF(A403="","",DATE(YEAR(A403),MONTH(A403),1))
G404: =IF(B404="","",IFERROR(VLOOKUP(B404,Справочники!$A$4:$C$18,2,FALSE()),"нет в справочнике")) | H404: =IF(A404="","",DATE(YEAR(A404),MONTH(A404),1))
G405: =IF(B405="","",IFERROR(VLOOKUP(B405,Справочники!$A$4:$C$18,2,FALSE()),"нет в справочнике")) | H405: =IF(A405="","",DATE(YEAR(A405),MONTH(A405),1))
G406: =IF(B406="","",IFERROR(VLOOKUP(B406,Справочники!$A$4:$C$18,2,FALSE()),"нет в справочнике")) | H406: =IF(A406="","",DATE(YEAR(A406),MONTH(A406),1))
G407: =IF(B407="","",IFERROR(VLOOKUP(B407,Справочники!$A$4:$C$18,2,FALSE()),"нет в справочнике")) | H407: =IF(A407="","",DATE(YEAR(A407),MONTH(A407),1))
G408: =IF(B408="","",IFERROR(VLOOKUP(B408,Справочники!$A$4:$C$18,2,FALSE()),"нет в справочнике")) | H408: =IF(A408="","",DATE(YEAR(A408),MONTH(A408),1))
G409: =IF(B409="","",IFERROR(VLOOKUP(B409,Справочники!$A$4:$C$18,2,FALSE()),"нет в справочнике")) | H409: =IF(A409="","",DATE(YEAR(A409),MONTH(A409),1))
G410: =IF(B410="","",IFERROR(VLOOKUP(B410,Справочники!$A$4:$C$18,2,FALSE()),"нет в справочнике")) | H410: =IF(A410="","",DATE(YEAR(A410),MONTH(A410),1))
G411: =IF(B411="","",IFERROR(VLOOKUP(B411,Справочники!$A$4:$C$18,2,FALSE()),"нет в справочнике")) | H411: =IF(A411="","",DATE(YEAR(A411),MONTH(A411),1))
G412: =IF(B412="","",IFERROR(VLOOKUP(B412,Справочники!$A$4:$C$18,2,FALSE()),"нет в справочнике")) | H412: =IF(A412="","",DATE(YEAR(A412),MONTH(A412),1))
G413: =IF(B413="","",IFERROR(VLOOKUP(B413,Справочники!$A$4:$C$18,2,FALSE()),"нет в справочнике")) | H413: =IF(A413="","",DATE(YEAR(A413),MONTH(A413),1))
... G441: =IF(B441="","",IFERROR(VLOOKUP(B441,Справочники!$A$4:$C$18,2,FALSE()),"нет в справочнике")) | H441: =IF(A441="","",DATE(YEAR(A441),MONTH(A441),1))

Sheet Сводка по месяцам
A1: Столярная мастерская «Верстак-12» · сводка за 2025 год, формулы СУММЕСЛИМН
A3: Показатель | B3: =DATE(2025,1,1) -> 45658 | C3: =DATE(2025,2,1) -> 45689 | D3: =DATE(2025,3,1) -> 45717 | E3: =DATE(2025,4,1) -> 45748 | F3: =DATE(2025,5,1) -> 45778 | G3: =DATE(2025,6,1) -> 45809 | H3: =DATE(2025,7,1) -> 45839 | I3: =DATE(2025,8,1) -> 45870 | J3: =DATE(2025,9,1) -> 45901 | K3: =DATE(2025,10,1) -> 45931 | L3: =DATE(2025,11,1) -> 45962 | M3: =DATE(2025,12,1) -> 45992 | N3: Итого за год
A4: ДОХОДЫ
A5: Продажа кухонь | B5: =SUMIFS(Операции!$E$3:$E$1000,Операции!$B$3:$B$1000,$A5,Операции!$H$3:$H$1000,B$3) -> 773800 | C5: =SUMIFS(Операции!$E$3:$E$1000,Операции!$B$3:$B$1000,$A5,Операции!$H$3:$H$1000,C$3) -> 646500 | D5: =SUMIFS(Операции!$E$3:$E$1000,Операции!$B$3:$B$1000,$A5,Операции!$H$3:$H$1000,D$3) -> 987200 | E5: =SUMIFS(Операции!$E$3:$E$1000,Операции!$B$3:$B$1000,$A5,Операции!$H$3:$H$1000,E$3) -> 1155100 | F5: =SUMIFS(Операции!$E$3:$E$1000,Операции!$B$3:$B$1000,$A5,Операции!$H$3:$H$1000,F$3) -> 713300 | G5: =SUMIFS(Операции!$E$3:$E$1000,Операции!$B$3:$B$1000,$A5,Операции!$H$3:$H$1000,G$3) -> 914800 | H5: =SUMIFS(Операции!$E$3:$E$1000,Операции!$B$3:$B$1000,$A5,Операции!$H$3:$H$1000,H$3) -> 1049100 | I5: =SUMIFS(Операции!$E$3:$E$1000,Операции!$B$3:$B$1000,$A5,Операции!$H$3:$H$1000,I$3) -> 1088400 | ... M5: =SUMIFS(Операции!$E$3:$E$1000,Операции!$B$3:$B$1000,$A5,Операции!$H$3:$H$1000,M$3) -> 743900 | N5: =SUM(B5:M5) -> 11908600
A6: Продажа шкафов | B6: =SUMIFS(Операции!$E$3:$E$1000,Операции!$B$3:$B$1000,$A6,Операции!$H$3:$H$1000,B$3) -> 293000 | C6: =SUMIFS(Операции!$E$3:$E$1000,Операции!$B$3:$B$1000,$A6,Операции!$H$3:$H$1000,C$3) -> 457200 | D6: =SUMIFS(Операции!$E$3:$E$1000,Операции!$B$3:$B$1000,$A6,Операции!$H$3:$H$1000,D$3) -> 665100 | E6: =SUMIFS(Операции!$E$3:$E$1000,Операции!$B$3:$B$1000,$A6,Операции!$H$3:$H$1000,E$3) -> 600500 | F6: =SUMIFS(Операции!$E$3:$E$1000,Операции!$B$3:$B$1000,$A6,Операции!$H$3:$H$1000,F$3) -> 400800 | G6: =SUMIFS(Операции!$E$3:$E$1000,Операции!$B$3:$B$1000,$A6,Операции!$H$3:$H$1000,G$3) -> 593500 | H6: =SUMIFS(Операции!$E$3:$E$1000,Операции!$B$3:$B$1000,$A6,Операции!$H$3:$H$1000,H$3) -> 415700 | I6: =SUMIFS(Операции!$E$3:$E$1000,Операции!$B$3:$B$1000,$A6,Операции!$H$3:$H$1000,I$3) -> 474000 | ... M6: =SUMIFS(Операции!$E$3:$E$1000,Операции!$B$3:$B$1000,$A6,Операции!$H$3:$H$1000,M$3) -> 520800 | N6: =SUM(B6:M6) -> 6611600
A7: Мелкая мебель | B7: =SUMIFS(Операции!$E$3:$E$1000,Операции!$B$3:$B$1000,$A7,Операции!$H$3:$H$1000,B$3) -> 23100 | C7: =SUMIFS(Операции!$E$3:$E$1000,Операции!$B$3:$B$1000,$A7,Операции!$H$3:$H$1000,C$3) -> 93900 | D7: =SUMIFS(Операции!$E$3:$E$1000,Операции!$B$3:$B$1000,$A7,Операции!$H$3:$H$1000,D$3) -> 69400 | E7: =SUMIFS(Операции!$E$3:$E$1000,Операции!$B$3:$B$1000,$A7,Операции!$H$3:$H$1000,E$3) -> 62900 | F7: =SUMIFS(Операции!$E$3:$E$1000,Операции!$B$3:$B$1000,$A7,Операции!$H$3:$H$1000,F$3) -> 88200 | G7: =SUMIFS(Операции!$E$3:$E$1000,Операции!$B$3:$B$1000,$A7,Операции!$H$3:$H$1000,G$3) -> 62100 | H7: =SUMIFS(Операции!$E$3:$E$1000,Операции!$B$3:$B$1000,$A7,Операции!$H$3:$H$1000,H$3) -> 103200 | I7: =SUMIFS(Операции!$E$3:$E$1000,Операции!$B$3:$B$1000,$A7,Операции!$H$3:$H$1000,I$3) -> 143600 | ... M7: =SUMIFS(Операции!$E$3:$E$1000,Операции!$B$3:$B$1000,$A7,Операции!$H$3:$H$1000,M$3) -> 52700 | N7: =SUM(B7:M7) -> 1066600
A8: Монтаж и доставка | B8: =SUMIFS(Операции!$E$3:$E$1000,Операции!$B$3:$B$1000,$A8,Операции!$H$3:$H$1000,B$3) -> 56300 | C8: =SUMIFS(Операции!$E$3:$E$1000,Операции!$B$3:$B$1000,$A8,Операции!$H$3:$H$1000,C$3) -> 50800 | D8: =SUMIFS(Операции!$E$3:$E$1000,Операции!$B$3:$B$1000,$A8,Операции!$H$3:$H$1000,D$3) -> 77700 | E8: =SUMIFS(Операции!$E$3:$E$1000,Операции!$B$3:$B$1000,$A8,Операции!$H$3:$H$1000,E$3) -> 50400 | F8: =SUMIFS(Операции!$E$3:$E$1000,Операции!$B$3:$B$1000,$A8,Операции!$H$3:$H$1000,F$3) -> 45600 | G8: =SUMIFS(Операции!$E$3:$E$1000,Операции!$B$3:$B$1000,$A8,Операции!$H$3:$H$1000,G$3) -> 53000 | H8: =SUMIFS(Операции!$E$3:$E$1000,Операции!$B$3:$B$1000,$A8,Операции!$H$3:$H$1000,H$3) -> 55200 | I8: =SUMIFS(Операции!$E$3:$E$1000,Операции!$B$3:$B$1000,$A8,Операции!$H$3:$H$1000,I$3) -> 66000 | ... M8: =SUMIFS(Операции!$E$3:$E$1000,Операции!$B$3:$B$1000,$A8,Операции!$H$3:$H$1000,M$3) -> 83800 | N8: =SUM(B8:M8) -> 744600
A9: Итого доходы | B9: =SUM(B5:B8) -> 1146200 | C9: =SUM(C5:C8) -> 1248400 | D9: =SUM(D5:D8) -> 1799400 | E9: =SUM(E5:E8) -> 1868900 | F9: =SUM(F5:F8) -> 1247900 | G9: =SUM(G5:G8) -> 1623400 | H9: =SUM(H5:H8) -> 1623200 | I9: =SUM(I5:I8) -> 1772000 | ... M9: =SUM(M5:M8) -> 1401200 | N9: =SUM(B9:M9) -> 20331400
A10: РАСХОДЫ
A11: Материалы (ЛДСП, фасады) | B11: =SUMIFS(Операции!$E$3:$E$1000,Операции!$B$3:$B$1000,$A11,Операции!$H$3:$H$1000,B$3) -> 322400 | C11: =SUMIFS(Операции!$E$3:$E$1000,Операции!$B$3:$B$1000,$A11,Операции!$H$3:$H$1000,C$3) -> 373700 | D11: =SUMIFS(Операции!$E$3:$E$1000,Операции!$B$3:$B$1000,$A11,Операции!$H$3:$H$1000,D$3) -> 505200 | E11: =SUMIFS(Операции!$E$3:$E$1000,Операции!$B$3:$B$1000,$A11,Операции!$H$3:$H$1000,E$3) -> 575900 | F11: =SUMIFS(Операции!$E$3:$E$1000,Операции!$B$3:$B$1000,$A11,Операции!$H$3:$H$1000,F$3) -> 366900 | G11: =SUMIFS(Операции!$E$3:$E$1000,Операции!$B$3:$B$1000,$A11,Операции!$H$3:$H$1000,G$3) -> 473300 | H11: =SUMIFS(Операции!$E$3:$E$1000,Операции!$B$3:$B$1000,$A11,Операции!$H$3:$H$1000,H$3) -> 488800 | I11: =SUMIFS(Операции!$E$3:$E$1000,Операции!$B$3:$B$1000,$A11,Операции!$H$3:$H$1000,I$3) -> 555100 | ... M11: =SUMIFS(Операции!$E$3:$E$1000,Операции!$B$3:$B$1000,$A11,Операции!$H$3:$H$1000,M$3) -> 414900 | N11: =SUM(B11:M11) -> 6059600
A12: Фурнитура | B12: =SUMIFS(Операции!$E$3:$E$1000,Операции!$B$3:$B$1000,$A12,Операции!$H$3:$H$1000,B$3) -> 93600 | C12: =SUMIFS(Операции!$E$3:$E$1000,Операции!$B$3:$B$1000,$A12,Операции!$H$3:$H$1000,C$3) -> 103500 | D12: =SUMIFS(Операции!$E$3:$E$1000,Операции!$B$3:$B$1000,$A12,Операции!$H$3:$H$1000,D$3) -> 138900 | E12: =SUMIFS(Операции!$E$3:$E$1000,Операции!$B$3:$B$1000,$A12,Операции!$H$3:$H$1000,E$3) -> 148000 | F12: =SUMIFS(Операции!$E$3:$E$1000,Операции!$B$3:$B$1000,$A12,Операции!$H$3:$H$1000,F$3) -> 104300 | G12: =SUMIFS(Операции!$E$3:$E$1000,Операции!$B$3:$B$1000,$A12,Операции!$H$3:$H$1000,G$3) -> 126800 | H12: =SUMIFS(Операции!$E$3:$E$1000,Операции!$B$3:$B$1000,$A12,Операции!$H$3:$H$1000,H$3) -> 120300 | I12: =SUMIFS(Операции!$E$3:$E$1000,Операции!$B$3:$B$1000,$A12,Операции!$H$3:$H$1000,I$3) -> 146800 | ... M12: =SUMIFS(Операции!$E$3:$E$1000,Операции!$B$3:$B$1000,$A12,Операции!$H$3:$H$1000,M$3) -> 118300 | N12: =SUM(B12:M12) -> 1619800
A13: Сдельная оплата сборщиков | B13: =SUMIFS(Операции!$E$3:$E$1000,Операции!$B$3:$B$1000,$A13,Операции!$H$3:$H$1000,B$3) -> 126100 | C13: =SUMIFS(Операции!$E$3:$E$1000,Операции!$B$3:$B$1000,$A13,Операции!$H$3:$H$1000,C$3) -> 137300 | D13: =SUMIFS(Операции!$E$3:$E$1000,Операции!$B$3:$B$1000,$A13,Операции!$H$3:$H$1000,D$3) -> 197900 | E13: =SUMIFS(Операции!$E$3:$E$1000,Операции!$B$3:$B$1000,$A13,Операции!$H$3:$H$1000,E$3) -> 205600 | F13: =SUMIFS(Операции!$E$3:$E$1000,Операции!$B$3:$B$1000,$A13,Операции!$H$3:$H$1000,F$3) -> 137300 | G13: =SUMIFS(Операции!$E$3:$E$1000,Операции!$B$3:$B$1000,$A13,Операции!$H$3:$H$1000,G$3) -> 178600 | H13: =SUMIFS(Операции!$E$3:$E$1000,Операции!$B$3:$B$1000,$A13,Операции!$H$3:$H$1000,H$3) -> 178600 | I13: =SUMIFS(Операции!$E$3:$E$1000,Операции!$B$3:$B$1000,$A13,Операции!$H$3:$H$1000,I$3) -> 194900 | ... M13: =SUMIFS(Операции!$E$3:$E$1000,Операции!$B$3:$B$1000,$A13,Операции!$H$3:$H$1000,M$3) -> 154100 | N13: =SUM(B13:M13) -> 2236400
A14: Транспорт | B14: =SUMIFS(Операции!$E$3:$E$1000,Операции!$B$3:$B$1000,$A14,Операции!$H$3:$H$1000,B$3) -> 30700 | C14: =SUMIFS(Операции!$E$3:$E$1000,Операции!$B$3:$B$1000,$A14,Операции!$H$3:$H$1000,C$3) -> 34900 | D14: =SUMIFS(Операции!$E$3:$E$1000,Операции!$B$3:$B$1000,$A14,Операции!$H$3:$H$1000,D$3) -> 42500 | E14: =SUMIFS(Операции!$E$3:$E$1000,Операции!$B$3:$B$1000,$A14,Операции!$H$3:$H$1000,E$3) -> 39300 | F14: =SUMIFS(Операции!$E$3:$E$1000,Операции!$B$3:$B$1000,$A14,Операции!$H$3:$H$1000,F$3) -> 26400 | G14: =SUMIFS(Операции!$E$3:$E$1000,Операции!$B$3:$B$1000,$A14,Операции!$H$3:$H$1000,G$3) -> 33300 | H14: =SUMIFS(Операции!$E$3:$E$1000,Операции!$B$3:$B$1000,$A14,Операции!$H$3:$H$1000,H$3) -> 44700 | I14: =SUMIFS(Операции!$E$3:$E$1000,Операции!$B$3:$B$1000,$A14,Операции!$H$3:$H$1000,I$3) -> 53100 | ... M14: =SUMIFS(Операции!$E$3:$E$1000,Операции!$B$3:$B$1000,$A14,Операции!$H$3:$H$1000,M$3) -> 40800 | N14: =SUM(B14:M14) -> 528300
A15: Зарплата (оклады) | B15: =SUMIFS(Операции!$E$3:$E$1000,Операции!$B$3:$B$1000,$A15,Операции!$H$3:$H$1000,B$3) -> 210000 | C15: =SUMIFS(Операции!$E$3:$E$1000,Операции!$B$3:$B$1000,$A15,Операции!$H$3:$H$1000,C$3) -> 210000 | D15: =SUMIFS(Операции!$E$3:$E$1000,Операции!$B$3:$B$1000,$A15,Операции!$H$3:$H$1000,D$3) -> 210000 | E15: =SUMIFS(Операции!$E$3:$E$1000,Операции!$B$3:$B$1000,$A15,Операции!$H$3:$H$1000,E$3) -> 210000 | F15: =SUMIFS(Операции!$E$3:$E$1000,Операции!$B$3:$B$1000,$A15,Операции!$H$3:$H$1000,F$3) -> 210000 | G15: =SUMIFS(Операции!$E$3:$E$1000,Операции!$B$3:$B$1000,$A15,Операции!$H$3:$H$1000,G$3) -> 210000 | H15: =SUMIFS(Операции!$E$3:$E$1000,Операции!$B$3:$B$1000,$A15,Операции!$H$3:$H$1000,H$3) -> 210000 | I15: =SUMIFS(Операции!$E$3:$E$1000,Операции!$B$3:$B$1000,$A15,Операции!$H$3:$H$1000,I$3) -> 210000 | ... M15: =SUMIFS(Операции!$E$3:$E$1000,Операции!$B$3:$B$1000,$A15,Операции!$H$3:$H$1000,M$3) -> 210000 | N15: =SUM(B15:M15) -> 2520000
A16: Аренда цеха | B16: =SUMIFS(Операции!$E$3:$E$1000,Операции!$B$3:$B$1000,$A16,Операции!$H$3:$H$1000,B$3) -> 85000 | C16: =SUMIFS(Операции!$E$3:$E$1000,Операции!$B$3:$B$1000,$A16,Операции!$H$3:$H$1000,C$3) -> 85000 | D16: =SUMIFS(Операции!$E$3:$E$1000,Операции!$B$3:$B$1000,$A16,Операции!$H$3:$H$1000,D$3) -> 85000 | E16: =SUMIFS(Операции!$E$3:$E$1000,Операции!$B$3:$B$1000,$A16,Операции!$H$3:$H$1000,E$3) -> 85000 | F16: =SUMIFS(Операции!$E$3:$E$1000,Операции!$B$3:$B$1000,$A16,Операции!$H$3:$H$1000,F$3) -> 85000 | G16: =SUMIFS(Операции!$E$3:$E$1000,Операции!$B$3:$B$1000,$A16,Операции!$H$3:$H$1000,G$3) -> 85000 | H16: =SUMIFS(Операции!$E$3:$E$1000,Операции!$B$3:$B$1000,$A16,Операции!$H$3:$H$1000,H$3) -> 85000 | I16: =SUMIFS(Операции!$E$3:$E$1000,Операции!$B$3:$B$1000,$A16,Операции!$H$3:$H$1000,I$3) -> 85000 | ... M16: =SUMIFS(Операции!$E$3:$E$1000,Операции!$B$3:$B$1000,$A16,Операции!$H$3:$H$1000,M$3) -> 85000 | N16: =SUM(B16:M16) -> 1020000
A17: Коммунальные услуги | B17: =SUMIFS(Операции!$E$3:$E$1000,Операции!$B$3:$B$1000,$A17,Операции!$H$3:$H$1000,B$3) -> 18900 | C17: =SUMIFS(Операции!$E$3:$E$1000,Операции!$B$3:$B$1000,$A17,Операции!$H$3:$H$1000,C$3) -> 32200 | D17: =SUMIFS(Операции!$E$3:$E$1000,Операции!$B$3:$B$1000,$A17,Операции!$H$3:$H$1000,D$3) -> 18900 | E17: =SUMIFS(Операции!$E$3:$E$1000,Операции!$B$3:$B$1000,$A17,Операции!$H$3:$H$1000,E$3) -> 24100 | F17: =SUMIFS(Операции!$E$3:$E$1000,Операции!$B$3:$B$1000,$A17,Операции!$H$3:$H$1000,F$3) -> 21000 | G17: =SUMIFS(Операции!$E$3:$E$1000,Операции!$B$3:$B$1000,$A17,Операции!$H$3:$H$1000,G$3) -> 14600 | H17: =SUMIFS(Операции!$E$3:$E$1000,Операции!$B$3:$B$1000,$A17,Операции!$H$3:$H$1000,H$3) -> 17400 | I17: =SUMIFS(Операции!$E$3:$E$1000,Операции!$B$3:$B$1000,$A17,Операции!$H$3:$H$1000,I$3) -> 20700 | ... M17: =SUMIFS(Операции!$E$3:$E$1000,Операции!$B$3:$B$1000,$A17,Операции!$H$3:$H$1000,M$3) -> 30600 | N17: =SUM(B17:M17) -> 258700
A18: Реклама | B18: =SUMIFS(Операции!$E$3:$E$1000,Операции!$B$3:$B$1000,$A18,Операции!$H$3:$H$1000,B$3) -> 40400 | C18: =SUMIFS(Операции!$E$3:$E$1000,Операции!$B$3:$B$1000,$A18,Операции!$H$3:$H$1000,C$3) -> 35700 | D18: =SUMIFS(Операции!$E$3:$E$1000,Операции!$B$3:$B$1000,$A18,Операции!$H$3:$H$1000,D$3) -> 37000 | E18: =SUMIFS(Операции!$E$3:$E$1000,Операции!$B$3:$B$1000,$A18,Операции!$H$3:$H$1000,E$3) -> 33500 | F18: =SUMIFS(Операции!$E$3:$E$1000,Операции!$B$3:$B$1000,$A18,Операции!$H$3:$H$1000,F$3) -> 28500 | G18: =SUMIFS(Операции!$E$3:$E$1000,Операции!$B$3:$B$1000,$A18,Операции!$H$3:$H$1000,G$3) -> 35600 | H18: =SUMIFS(Операции!$E$3:$E$1000,Операции!$B$3:$B$1000,$A18,Операции!$H$3:$H$1000,H$3) -> 40300 | I18: =SUMIFS(Операции!$E$3:$E$1000,Операции!$B$3:$B$1000,$A18,Операции!$H$3:$H$1000,I$3) -> 36400 | ... M18: =SUMIFS(Операции!$E$3:$E$1000,Операции!$B$3:$B$1000,$A18,Операции!$H$3:$H$1000,M$3) -> 42200 | N18: =SUM(B18:M18) -> 430100
A19: Инструмент и ремонт | B19: =SUMIFS(Операции!$E$3:$E$1000,Операции!$B$3:$B$1000,$A19,Операции!$H$3:$H$1000,B$3) -> 13500 | C19: =SUMIFS(Операции!$E$3:$E$1000,Операции!$B$3:$B$1000,$A19,Операции!$H$3:$H$1000,C$3) -> 0 | D19: =SUMIFS(Операции!$E$3:$E$1000,Операции!$B$3:$B$1000,$A19,Операции!$H$3:$H$1000,D$3) -> 32800 | E19: =SUMIFS(Операции!$E$3:$E$1000,Операции!$B$3:$B$1000,$A19,Операции!$H$3:$H$1000,E$3) -> 18700 | F19: =SUMIFS(Операции!$E$3:$E$1000,Операции!$B$3:$B$1000,$A19,Операции!$H$3:$H$1000,F$3) -> 27100 | G19: =SUMIFS(Операции!$E$3:$E$1000,Операции!$B$3:$B$1000,$A19,Операции!$H$3:$H$1000,G$3) -> 10100 | H19: =SUMIFS(Операции!$E$3:$E$1000,Операции!$B$3:$B$1000,$A19,Операции!$H$3:$H$1000,H$3) -> 6700 | I19: =SUMIFS(Операции!$E$3:$E$1000,Операции!$B$3:$B$1000,$A19,Операции!$H$3:$H$1000,I$3) -> 0 | ... M19: =SUMIFS(Операции!$E$3:$E$1000,Операции!$B$3:$B$1000,$A19,Операции!$H$3:$H$1000,M$3) -> 0 | N19: =SUM(B19:M19) -> 132400
A20: Бухгалтерия и банк | B20: =SUMIFS(Операции!$E$3:$E$1000,Операции!$B$3:$B$1000,$A20,Операции!$H$3:$H$1000,B$3) -> 12500 | C20: =SUMIFS(Операции!$E$3:$E$1000,Операции!$B$3:$B$1000,$A20,Операции!$H$3:$H$1000,C$3) -> 12500 | D20: =SUMIFS(Операции!$E$3:$E$1000,Операции!$B$3:$B$1000,$A20,Операции!$H$3:$H$1000,D$3) -> 12500 | E20: =SUMIFS(Операции!$E$3:$E$1000,Операции!$B$3:$B$1000,$A20,Операции!$H$3:$H$1000,E$3) -> 12500 | F20: =SUMIFS(Операции!$E$3:$E$1000,Операции!$B$3:$B$1000,$A20,Операции!$H$3:$H$1000,F$3) -> 12500 | G20: =SUMIFS(Операции!$E$3:$E$1000,Операции!$B$3:$B$1000,$A20,Операции!$H$3:$H$1000,G$3) -> 12500 | H20: =SUMIFS(Операции!$E$3:$E$1000,Операции!$B$3:$B$1000,$A20,Операции!$H$3:$H$1000,H$3) -> 12500 | I20: =SUMIFS(Операции!$E$3:$E$1000,Операции!$B$3:$B$1000,$A20,Операции!$H$3:$H$1000,I$3) -> 12500 | ... M20: =SUMIFS(Операции!$E$3:$E$1000,Операции!$B$3:$B$1000,$A20,Операции!$H$3:$H$1000,M$3) -> 12500 | N20: =SUM(B20:M20) -> 150000
A21: Налоги (УСН) | B21: =SUMIFS(Операции!$E$3:$E$1000,Операции!$B$3:$B$1000,$A21,Операции!$H$3:$H$1000,B$3) -> 0 | C21: =SUMIFS(Операции!$E$3:$E$1000,Операции!$B$3:$B$1000,$A21,Операции!$H$3:$H$1000,C$3) -> 0 | D21: =SUMIFS(Операции!$E$3:$E$1000,Операции!$B$3:$B$1000,$A21,Операции!$H$3:$H$1000,D$3) -> 0 | E21: =SUMIFS(Операции!$E$3:$E$1000,Операции!$B$3:$B$1000,$A21,Операции!$H$3:$H$1000,E$3) -> 251600 | F21: =SUMIFS(Операции!$E$3:$E$1000,Операции!$B$3:$B$1000,$A21,Операции!$H$3:$H$1000,F$3) -> 0 | G21: =SUMIFS(Операции!$E$3:$E$1000,Операции!$B$3:$B$1000,$A21,Операции!$H$3:$H$1000,G$3) -> 0 | H21: =SUMIFS(Операции!$E$3:$E$1000,Операции!$B$3:$B$1000,$A21,Операции!$H$3:$H$1000,H$3) -> 284400 | I21: =SUMIFS(Операции!$E$3:$E$1000,Операции!$B$3:$B$1000,$A21,Операции!$H$3:$H$1000,I$3) -> 0 | ... M21: =SUMIFS(Операции!$E$3:$E$1000,Операции!$B$3:$B$1000,$A21,Операции!$H$3:$H$1000,M$3) -> 371000 | N21: =SUM(B21:M21) -> 1219900
A22: Итого расходы | B22: =SUM(B11:B21) -> 953100 | C22: =SUM(C11:C21) -> 1024800 | D22: =SUM(D11:D21) -> 1280700 | E22: =SUM(E11:E21) -> 1604200 | F22: =SUM(F11:F21) -> 1019000 | G22: =SUM(G11:G21) -> 1179800 | H22: =SUM(H11:H21) -> 1488700 | I22: =SUM(I11:I21) -> 1314500 | ... M22: =SUM(M11:M21) -> 1479400 | N22: =SUM(B22:M22) -> 16175200
A23: РЕЗУЛЬТАТ
A24: Переменные расходы | B24: =SUM(B11:B14) -> 572800 | C24: =SUM(C11:C14) -> 649400 | D24: =SUM(D11:D14) -> 884500 | E24: =SUM(E11:E14) -> 968800 | F24: =SUM(F11:F14) -> 634900 | G24: =SUM(G11:G14) -> 812000 | H24: =SUM(H11:H14) -> 832400 | I24: =SUM(I11:I14) -> 949900 | ... M24: =SUM(M11:M14) -> 728100 | N24: =SUM(B24:M24) -> 10444100
A25: Маржинальная прибыль | B25: =B9-B24 -> 573400 | C25: =C9-C24 -> 599000 | D25: =D9-D24 -> 914900 | E25: =E9-E24 -> 900100 | F25: =F9-F24 -> 613000 | G25: =G9-G24 -> 811400 | H25: =H9-H24 -> 790800 | I25: =I9-I24 -> 822100 | ... M25: =M9-M24 -> 673100 | N25: =SUM(B25:M25) -> 9887300
A26: Чистая прибыль | B26: =B9-B22 -> 193100 | C26: =C9-C22 -> 223600 | D26: =D9-D22 -> 518700 | E26: =E9-E22 -> 264700 | F26: =F9-F22 -> 228900 | G26: =G9-G22 -> 443600 | H26: =H9-H22 -> 134500 | I26: =I9-I22 -> 457500 | ... M26: =M9-M22 -> -78200 | N26: =SUM(B26:M26) -> 4156200
A27: Рентабельность | B27: =IF(B9=0,0,B26/B9) -> 0.16846973 | C27: =IF(C9=0,0,C26/C9) -> 0.17910926 | D27: =IF(D9=0,0,D26/D9) -> 0.28826275 | E27: =IF(E9=0,0,E26/E9) -> 0.14163412 | F27: =IF(F9=0,0,F26/F9) -> 0.18342816 | G27: =IF(G9=0,0,G26/G9) -> 0.27325367 | H27: =IF(H9=0,0,H26/H9) -> 0.082861015 | I27: =IF(I9=0,0,I26/I9) -> 0.25818284 | ... N27: =IF(N9=0,0,N26/N9) -> 0.20442272
A28: Остаток денег на конец месяца | B28: =Справочники!$H$7+SUM($B26:B26) -> 708100 | C28: =Справочники!$H$7+SUM($B26:C26) -> 931700 | D28: =Справочники!$H$7+SUM($B26:D26) -> 1450400 | E28: =Справочники!$H$7+SUM($B26:E26) -> 1715100 | F28: =Справочники!$H$7+SUM($B26:F26) -> 1944000 | G28: =Справочники!$H$7+SUM($B26:G26) -> 2387600 | H28: =Справочники!$H$7+SUM($B26:H26) -> 2522100 | I28: =Справочники!$H$7+SUM($B26:I26) -> 2979600 | ... M28: =Справочники!$H$7+SUM($B26:M26) -> 4671200 | N28: =M28 -> 4671200
A30: ВЫРУЧКА ПО НАПРАВЛЕНИЯМ
A31: Кухни | B31: =SUMIFS(Операции!$E$3:$E$1000,Операции!$C$3:$C$1000,$A31,Операции!$G$3:$G$1000,"Доход",Операции!$H$3:$H$1000,B$3) -> 820300 | C31: =SUMIFS(Операции!$E$3:$E$1000,Операции!$C$3:$C$1000,$A31,Операции!$G$3:$G$1000,"Доход",Операции!$H$3:$H$1000,C$3) -> 658700 | D31: =SUMIFS(Операции!$E$3:$E$1000,Операции!$C$3:$C$1000,$A31,Операции!$G$3:$G$1000,"Доход",Операции!$H$3:$H$1000,D$3) -> 1016600 | E31: =SUMIFS(Операции!$E$3:$E$1000,Операции!$C$3:$C$1000,$A31,Операции!$G$3:$G$1000,"Доход",Операции!$H$3:$H$1000,E$3) -> 1183800 | F31: =SUMIFS(Операции!$E$3:$E$1000,Операции!$C$3:$C$1000,$A31,Операции!$G$3:$G$1000,"Доход",Операции!$H$3:$H$1000,F$3) -> 713300 | G31: =SUMIFS(Операции!$E$3:$E$1000,Операции!$C$3:$C$1000,$A31,Операции!$G$3:$G$1000,"Доход",Операции!$H$3:$H$1000,G$3) -> 931000 | H31: =SUMIFS(Операции!$E$3:$E$1000,Операции!$C$3:$C$1000,$A31,Операции!$G$3:$G$1000,"Доход",Операции!$H$3:$H$1000,H$3) -> 1077100 | I31: =SUMIFS(Операции!$E$3:$E$1000,Операции!$C$3:$C$1000,$A31,Операции!$G$3:$G$1000,"Доход",Операции!$H$3:$H$1000,I$3) -> 1125700 | ... M31: =SUMIFS(Операции!$E$3:$E$1000,Операции!$C$3:$C$1000,$A31,Операции!$G$3:$G$1000,"Доход",Операции!$H$3:$H$1000,M$3) -> 765800 | N31: =SUM(B31:M31) -> 12255200
A32: Шкафы и гардеробные | B32: =SUMIFS(Операции!$E$3:$E$1000,Операции!$C$3:$C$1000,$A32,Операции!$G$3:$G$1000,"Доход",Операции!$H$3:$H$1000,B$3) -> 302800 | C32: =SUMIFS(Операции!$E$3:$E$1000,Операции!$C$3:$C$1000,$A32,Операции!$G$3:$G$1000,"Доход",Операции!$H$3:$H$1000,C$3) -> 495800 | D32: =SUMIFS(Операции!$E$3:$E$1000,Операции!$C$3:$C$1000,$A32,Операции!$G$3:$G$1000,"Доход",Операции!$H$3:$H$1000,D$3) -> 713400 | E32: =SUMIFS(Операции!$E$3:$E$1000,Операции!$C$3:$C$1000,$A32,Операции!$G$3:$G$1000,"Доход",Операции!$H$3:$H$1000,E$3) -> 622200 | F32: =SUMIFS(Операции!$E$3:$E$1000,Операции!$C$3:$C$1000,$A32,Операции!$G$3:$G$1000,"Доход",Операции!$H$3:$H$1000,F$3) -> 446400 | G32: =SUMIFS(Операции!$E$3:$E$1000,Операции!$C$3:$C$1000,$A32,Операции!$G$3:$G$1000,"Доход",Операции!$H$3:$H$1000,G$3) -> 630300 | H32: =SUMIFS(Операции!$E$3:$E$1000,Операции!$C$3:$C$1000,$A32,Операции!$G$3:$G$1000,"Доход",Операции!$H$3:$H$1000,H$3) -> 442900 | I32: =SUMIFS(Операции!$E$3:$E$1000,Операции!$C$3:$C$1000,$A32,Операции!$G$3:$G$1000,"Доход",Операции!$H$3:$H$1000,I$3) -> 502700 | ... M32: =SUMIFS(Операции!$E$3:$E$1000,Операции!$C$3:$C$1000,$A32,Операции!$G$3:$G$1000,"Доход",Операции!$H$3:$H$1000,M$3) -> 582700 | N32: =SUM(B32:M32) -> 7009600
A33: Мелкая мебель | B33: =SUMIFS(Операции!$E$3:$E$1000,Операции!$C$3:$C$1000,$A33,Операции!$G$3:$G$1000,"Доход",Операции!$H$3:$H$1000,B$3) -> 23100 | C33: =SUMIFS(Операции!$E$3:$E$1000,Операции!$C$3:$C$1000,$A33,Операции!$G$3:$G$1000,"Доход",Операции!$H$3:$H$1000,C$3) -> 93900 | D33: =SUMIFS(Операции!$E$3:$E$1000,Операции!$C$3:$C$1000,$A33,Операции!$G$3:$G$1000,"Доход",Операции!$H$3:$H$1000,D$3) -> 69400 | E33: =SUMIFS(Операции!$E$3:$E$1000,Операции!$C$3:$C$1000,$A33,Операции!$G$3:$G$1000,"Доход",Операции!$H$3:$H$1000,E$3) -> 62900 | F33: =SUMIFS(Операции!$E$3:$E$1000,Операции!$C$3:$C$1000,$A33,Операции!$G$3:$G$1000,"Доход",Операции!$H$3:$H$1000,F$3) -> 88200 | G33: =SUMIFS(Операции!$E$3:$E$1000,Операции!$C$3:$C$1000,$A33,Операции!$G$3:$G$1000,"Доход",Операции!$H$3:$H$1000,G$3) -> 62100 | H33: =SUMIFS(Операции!$E$3:$E$1000,Операции!$C$3:$C$1000,$A33,Операции!$G$3:$G$1000,"Доход",Операции!$H$3:$H$1000,H$3) -> 103200 | I33: =SUMIFS(Операции!$E$3:$E$1000,Операции!$C$3:$C$1000,$A33,Операции!$G$3:$G$1000,"Доход",Операции!$H$3:$H$1000,I$3) -> 143600 | ... M33: =SUMIFS(Операции!$E$3:$E$1000,Операции!$C$3:$C$1000,$A33,Операции!$G$3:$G$1000,"Доход",Операции!$H$3:$H$1000,M$3) -> 52700 | N33: =SUM(B33:M33) -> 1066600
A35: ПРОВЕРКА
A36: Операции без статьи в справочнике, шт. | B36: =COUNTIFS(Операции!$G$3:$G$1000,"нет в справочнике",Операции!$H$3:$H$1000,B$3) -> 0 | C36: =COUNTIFS(Операции!$G$3:$G$1000,"нет в справочнике",Операции!$H$3:$H$1000,C$3) -> 0 | D36: =COUNTIFS(Операции!$G$3:$G$1000,"нет в справочнике",Операции!$H$3:$H$1000,D$3) -> 0 | E36: =COUNTIFS(Операции!$G$3:$G$1000,"нет в справочнике",Операции!$H$3:$H$1000,E$3) -> 0 | F36: =COUNTIFS(Операции!$G$3:$G$1000,"нет в справочнике",Операции!$H$3:$H$1000,F$3) -> 0 | G36: =COUNTIFS(Операции!$G$3:$G$1000,"нет в справочнике",Операции!$H$3:$H$1000,G$3) -> 0 | H36: =COUNTIFS(Операции!$G$3:$G$1000,"нет в справочнике",Операции!$H$3:$H$1000,H$3) -> 0 | I36: =COUNTIFS(Операции!$G$3:$G$1000,"нет в справочнике",Операции!$H$3:$H$1000,I$3) -> 0 | ... M36: =COUNTIFS(Операции!$G$3:$G$1000,"нет в справочнике",Операции!$H$3:$H$1000,M$3) -> 0 | N36: =SUM(B36:M36) -> 0
